[
  {
    "action": "fundef",
    "name": "f",
    "arg": "a",
    "body": [
      {
        "action": "return",
        "expr": {
          "type": "var",
          "name": "a",
          "start_line": 4,
          "start_char": 11,
          "end_line": 4,
          "end_char": 12
        },
        "start_line": 4,
        "start_char": 4,
        "end_line": 4,
        "end_char": 13
      }
    ],
    "start_line": 3,
    "start_char": 0,
    "end_line": 5,
    "end_char": 1
  },
  {
    "action": "fundef",
    "name": "main",
    "arg": "argc",
    "body": [
      {
        "action": "vardef",
        "name": "x",
        "start_line": 9,
        "start_char": 4,
        "end_line": 9,
        "end_char": 10
      },
      {
        "action": "varset",
        "name": "x",
        "expr": {
          "type": "application",
          "function": "f",
          "argvalue": {
            "type": "cst",
            "value": 10,
            "start_line": 10,
            "start_char": 10,
            "end_line": 10,
            "end_char": 12
          },
          "start_line": 10,
          "start_char": 8,
          "end_line": 10,
          "end_char": 13
        },
        "start_line": 10,
        "start_char": 4,
        "end_line": 10,
        "end_char": 14
      },
      {
        "action": "print",
        "expr": {
          "type": "var",
          "name": "x",
          "start_line": 11,
          "start_char": 10,
          "end_line": 11,
          "end_char": 11
        },
        "start_line": 11,
        "start_char": 4,
        "end_line": 11,
        "end_char": 13
      },
      {
        "action": "return",
        "expr": {
          "type": "cst",
          "value": 0,
          "start_line": 12,
          "start_char": 11,
          "end_line": 12,
          "end_char": 12
        },
        "start_line": 12,
        "start_char": 4,
        "end_line": 12,
        "end_char": 13
      }
    ],
    "start_line": 8,
    "start_char": 0,
    "end_line": 13,
    "end_char": 1
  }
]
